run_ipynb/__init__.py
run_ipynb/cli.py
run_ipynb-0.1.1.dist-info/METADATA
run_ipynb-0.1.1.dist-info/WHEEL
run_ipynb-0.1.1.dist-info/entry_points.txt
run_ipynb-0.1.1.dist-info/RECORD
