Metadata-Version: 2.4
Name: run-ipynb
Version: 0.1.1
Summary: A tool to run Jupyter notebooks as Python scripts
Author-email: Darius Schaub <schaub.darius@gmail.com>
Requires-Python: >=3.7
Requires-Dist: jupyter==1.1.1
Requires-Dist: rich>=13.8.1
